handoff/__init__.py
handoff/core.py
handoff/guard.py
handoff/langgraph.py
handoff/retry.py
handoff/testing.py
handoff/utils.py
handoff_guard-0.1.0.dist-info/METADATA
handoff_guard-0.1.0.dist-info/WHEEL
handoff_guard-0.1.0.dist-info/licenses/LICENSE
handoff_guard-0.1.0.dist-info/RECORD
