Metadata-Version: 2.4
Name: handoff-guard
Version: 0.1.0
Summary: Lightweight validation at agent boundaries. Know what broke and where.
Project-URL: Homepage, https://github.com/acartag7/handoff-guard
Project-URL: Repository, https://github.com/acartag7/handoff-guard
Author-email: Arnold <cartagena.arnold@gmail.com>
License: MIT
License-File: LICENSE
Keywords: agents,handoff,langgraph,multi-agent,validation
Classifier: Development Status :: 3 - Alpha
Classifier: Intended Audience :: Developers
Classifier: License :: OSI Approved :: MIT License
Classifier: Programming Language :: Python :: 3.10
Classifier: Programming Language :: Python :: 3.11
Classifier: Programming Language :: Python :: 3.12
Requires-Python: >=3.10
Requires-Dist: pydantic>=2.0.0
Provides-Extra: dev
Requires-Dist: pre-commit>=3.0.0; extra == 'dev'
Requires-Dist: pytest-asyncio>=0.23.0; extra == 'dev'
Requires-Dist: pytest>=8.0.0; extra == 'dev'
Requires-Dist: ruff>=0.1.0; extra == 'dev'
Provides-Extra: langgraph
Requires-Dist: langgraph>=0.2.0; extra == 'langgraph'
Provides-Extra: llm
Requires-Dist: httpx>=0.25.0; extra == 'llm'
Requires-Dist: langgraph>=0.2.0; extra == 'llm'
